archyve/__init__.py
archyve/archyve.py
archyve/entry.py
archyve/examples.py
archyve/file_structure_functions.py
archyve/scripts/__init__.py
archyve/scripts/clean_image_lib.py
archyve/tests/__init__.py
archyve/tests/run_unit_tests.py
archyve/tests/test_entry.py
archyve/tests/test_file_structure_functions.py
archyve/tests/test_materials/entry/audio.mp3
archyve/tests/test_materials/entry/audio.wav
archyve/tests/test_materials/entry/black_square.jpg
archyve/tests/test_materials/entry/black_square1.jpg
archyve/tests/test_materials/entry/image.jpg
archyve/tests/test_materials/entry/image.png
archyve/tests/test_materials/entry/image_with_exif.jpg
archyve/tests/test_materials/entry/unknown
archyve/tests/test_materials/entry/unknown.1234
archyve/tests/test_materials/entry/video.mp4
archyve/tests/test_materials/entry/video.mpeg
archyve/tests/test_materials/file_structure_functions/sub_dirs/dir1/placeholder.txt
archyve/tests/test_materials/file_structure_functions/sub_dirs/dir2/placeholder.txt
archyve/tests/test_materials/file_structure_functions/sub_dirs/dir3/placeholder.txt
archyve/tests/test_materials/file_structure_functions/sub_dirs/dir4/placeholder.txt
archyve/tests/test_materials/file_structure_functions/sub_files/file1.txt
archyve/tests/test_materials/file_structure_functions/sub_files/file2.txt
archyve/tests/test_materials/file_structure_functions/sub_files/file3.txt
archyve/tests/test_materials/file_structure_functions/sub_files/file4.txt
archyve/tests/test_materials/file_structure_functions/sub_paths/dir1/file1.txt
archyve/tests/test_materials/file_structure_functions/sub_paths/dir1/file2.txt
archyve/tests/test_materials/file_structure_functions/sub_paths/dir1/file3.txt
archyve/tests/test_materials/file_structure_functions/sub_paths/dir1/file4.txt
archyve/tests/test_materials/file_structure_functions/sub_paths/dir2/file5.txt
archyve/tests/test_materials/file_structure_functions/sub_paths/dir2/file6.txt
archyve-0.2.8.dist-info/METADATA
archyve-0.2.8.dist-info/WHEEL
archyve-0.2.8.dist-info/RECORD
