Metadata-Version: 2.1
Name: archyve
Version: 0.2.8
Summary: Python toolkit for the mass management and analysis of files.
Author: Alistair Kellaway
Author-email: ali.kellaway139@gmail.com
Requires-Python: >=3.12,<4.0
Classifier: Programming Language :: Python :: 3
Classifier: Programming Language :: Python :: 3.12
Requires-Dist: pillow (>=10.3.0,<11.0.0)
